[
  {
    "farmhouse_id": 1,
    "id": 1,
    "orbs": "Quinoa",
    "category": "Whole-grain",
    "status": "IN STOCK",
    "quantity": 500
  },
  {
    "farmhouse_id": 2,
    "id": 2,
    "orbs": "Tomatoes",
    "category": "Vegetables",
    "status": "OUT OF STOCK",
    "quantity": 0
  },
  {
    "farmhouse_id": 3,
    "id": 3,
    "orbs": "Pumpkin Seeds",
    "category": "Seeds",
    "status": "OUT OF STOCK",
    "quantity": 0
  },
  {
    "farmhouse_id": 4,
    "id": 4,
    "orbs": " Barley Pearl",
    "category": "Whole-grain",
    "status": "IN STOCK",
    "quantity": 2000
  },
  {
    "farmhouse_id": 5,
    "id": 5,
    "orbs": "Bananas",
    "category": "Fruits",
    "status": "IN STOCK",
    "quantity": 4350
  },
  {
    "farmhouse_id": 6,
    "id": 6,
    "orbs": "Carrots",
    "category": "Vegetables",
    "status": "IN STOCK",
    "quantity": 10000
  },
  {
    "farmhouse_id": 7,
    "id": 7,
    "orbs": "Mangoes",
    "category": "Fruits",
    "status": "IN STOCK",
    "quantity": 800
  },
  {
    "farmhouse_id": 2,
    "id": 8,
    "orbs": "Almonds",
    "category": "Seeds",
    "status": "OUT OF STOCK",
    "quantity": 0
  }
]
